__init__.py
service_pb2.py
service_pb2.pyi
service_pb2_grpc.py
vendor/__init__.py
vendor/validate_pb2.py
vendor/validate_pb2.pyi
vendor/validate_pb2_grpc.py
orca_python/__init__.py
orca_python/envs.py
orca_python/exceptions.py
orca_python/main.py
orca_python/py.typed
orca_time-0.1.1.dist-info/LICENSE
orca_time-0.1.1.dist-info/METADATA
orca_time-0.1.1.dist-info/WHEEL
orca_time-0.1.1.dist-info/RECORD
