Metadata-Version: 2.3
Name: orca-time
Version: 0.1.1
Summary: 
Author: Frederick Mannings
Author-email: contact@predixus.com
Requires-Python: >=3.10
Classifier: Programming Language :: Python :: 3
Classifier: Programming Language :: Python :: 3.10
Classifier: Programming Language :: Python :: 3.11
Classifier: Programming Language :: Python :: 3.12
Classifier: Programming Language :: Python :: 3.13
Requires-Dist: grpcio (>=1.71.0,<2.0.0)
Requires-Dist: grpcio-tools (>=1.71.0,<2.0.0)
